{
  "artwork": [
    {
      "id": 0,
      "preview_img": "https://canantolon.b-cdn.net/demos/work/2013_Untitled_OilOnCanvas_8.3%20copy/SWN_Unt8_3_sl.jpg",
      "full_img": "https://canantolon.b-cdn.net/demos/work/2013_Untitled_OilOnCanvas_8.3%20copy/2013_Untitled_OilOnCanvas_8.3.jpg",
      "description": "Untitled 8.3, 2013, oil on canvas, 36\" x 24\" (92 x 61 cm)"
    },
    {
      "id": 1,
      "preview_img": "https://canantolon.b-cdn.net/demos/work/2009_UntitledOilOnLinen2%20copy/2009_UntitledOilOnLinen2.jpg",
      "full_img": "https://canantolon.b-cdn.net/demos/work/2009_UntitledOilOnLinen2%20copy/2009_UntitledOilOnLinen2.jpg",
      "description": "Untitled 2, 2009, oil on linen, 60\" x 45\" (152 x 114 cm)"
    },
    {
      "id": 2,
      "preview_img": "https://canantolon.b-cdn.net/demos/work/2011_Reflex17%20copy/Reflex17_sl.jpg",
      "full_img": "https://canantolon.b-cdn.net/demos/work/2011_Reflex17%20copy/2011_Reflex17.jpg",
      "description": "Reflex 17, 2011, oil on 4 panels, 72\" x 96\" (183 x 244 cm)"
    },
    {
      "id": 3,
      "preview_img": "https://canantolon.b-cdn.net/demos/work/2013_Untitled_OilOnCanvas_3.3%20copy/SWN_Unt3_3_sl.jpg",
      "full_img": "https://canantolon.b-cdn.net/demos/work/2013_Untitled_OilOnCanvas_3.3%20copy/2013_Untitled_OilOnCanvas_3.3.jpg",
      "description": "Untitled 3.3, 2013, oil on canvas, 14\" x 12\" (36 x 31 cm)"
    },
    {
      "id": 4,
      "preview_img": "https://canantolon.b-cdn.net/demos/work/2013_Untitled_OilOnPanel_4.2%20copy/SWN_Unt4_2_sl.jpg",
      "full_img": "https://canantolon.b-cdn.net/demos/work/2013_Untitled_OilOnPanel_4.2%20copy/2013_Untitled_OilOnPanel_4.2.jpg",
      "description": "Untitled 4.2, 2013, oil on panel, 24\" x 24\" (61 x 61 cm)"
    },
    {
      "id": 5,
      "preview_img": "https://canantolon.b-cdn.net/demos/work/2013_Untitled_Rust&Pigment%20copy/Rustdiptych_sl.jpg",
      "full_img": "https://canantolon.b-cdn.net/demos/work/2013_Untitled_Rust&Pigment%20copy/2013_Untitled_Rust&Pigment.jpg",
      "description": "Untitled 2013, rust and pigment on canvas, 48 \" x 96 \" (122 x 244 cm) "
    },
    {
      "id": 6,
      "preview_img": "https://canantolon.b-cdn.net/demos/work/2015_Agir_OilOnCanvas_1%20copy/AGIR_1_2015_sl.jpg",
      "full_img": "https://canantolon.b-cdn.net/demos/work/2015_Agir_OilOnCanvas_1%20copy/2015_Agir_OilOnCanvas_1.jpg",
      "description": "AGIR 1, 2015, oil on canvas, 76 \" x 248 \" (193 x 630 cm)"
    },
    {
      "id": 7,
      "preview_img": "https://canantolon.b-cdn.net/demos/work/2015_Agir_OilOnCanvas_2%20copy/AGIR_2_2015_sl.jpg",
      "full_img": "https://canantolon.b-cdn.net/demos/work/2015_Agir_OilOnCanvas_2%20copy/2015_Agir_OilOnCanvas_2.jpg",
      "description": "AGIR 2, 2015, oil on canvas, 76 \" x 240 \" (192 x 610 cm)"
    },
    {
      "id": 8,
      "preview_img": "https://canantolon.b-cdn.net/demos/work/2014%20Sidesteps%201%20copy/PU_1_Exhibition_2014_sl.jpg",
      "full_img": "https://canantolon.b-cdn.net/demos/work/2014%20Sidesteps%201%20copy/2014_1_Exhibition_Sidesteps.jpg",
      "description": "Sidesteps 2014, Parasol unit foundation for contemporary art, London"
    }
  ],
  "exhibitions": [
    {
      "title": "sidesteps",
      "year": "2014",
      "squares": [
        {
          "id": 0,
          "preview_img": "",
          "full_img": "",
          "description": ""
        },
        {
          "id": 1,
          "preview_img": "",
          "full_img": "",
          "description": ""
        },
        {
          "id": 2,
          "preview_img": "",
          "full_img": "",
          "description": ""
        }
      ]
    },
    {
      "title": "time after time",
      "year": 2012,
      "squares": [
        {
          "id": 0,
          "preview_img": "",
          "full_img": "",
          "description": ""
        },
        {
          "id": 1,
          "preview_img": "",
          "full_img": "",
          "description": ""
        },
        {
          "id": 2,
          "preview_img": "",
          "full_img": "",
          "description": ""
        }
      ]
    }
  ]
}